.travis.yml
NOTICE.txt
README.rst
bootstrap.py
buildout.cfg
eke.review.sublime-project
setup.cfg
setup.py
travis.cfg
docs/HISTORY.txt
docs/INSTALL.txt
docs/LICENSE.txt
eke/__init__.py
eke.review.egg-info/PKG-INFO
eke.review.egg-info/SOURCES.txt
eke.review.egg-info/dependency_links.txt
eke.review.egg-info/entry_points.txt
eke.review.egg-info/namespace_packages.txt
eke.review.egg-info/not-zip-safe
eke.review.egg-info/requires.txt
eke.review.egg-info/top_level.txt
eke/review/__init__.py
eke/review/config.py
eke/review/configure.zcml
eke/review/interfaces.py
eke/review/setuphandlers.py
eke/review/testing.py
eke/review/upgrades.py
eke/review/upgrades.zcml
eke/review/content/__init__.py
eke/review/content/configure.zcml
eke/review/content/urlfieldsetfolder.py
eke/review/profiles/default/eke.review.txt
eke/review/profiles/default/factorytool.xml
eke/review/profiles/default/metadata.xml
eke/review/profiles/default/propertiestool.xml
eke/review/profiles/default/skins.xml
eke/review/profiles/default/types.xml
eke/review/profiles/default/workflows.xml
eke/review/profiles/default/types/URLFieldsetFolder.xml
eke/review/skins/eke_review_custom_templates/widget_url_fieldset_start.pt
eke/review/tests/__init__.py
eke/review/tests/testSetup.py
eke/review/widgets/__init__.py
eke/review/widgets/fieldset.py